MANIFEST.in
README.md
setup.py
django_terralego/__init__.py
django_terralego/admin.py
django_terralego/apps.py
django_terralego/conf.py
django_terralego/models.py
django_terralego/views.py
django_terralego.egg-info/PKG-INFO
django_terralego.egg-info/SOURCES.txt
django_terralego.egg-info/dependency_links.txt
django_terralego.egg-info/not-zip-safe
django_terralego.egg-info/requires.txt
django_terralego.egg-info/top_level.txt